moead_framework/__init__.py
moead_framework/aggregation/__init__.py
moead_framework/aggregation/functions.py
moead_framework/aggregation/tchebycheff.py
moead_framework/aggregation/weighted_sum.py
moead_framework/algorithm/__init__.py
moead_framework/algorithm/abstract_moead.py
moead_framework/algorithm/combinatorial/__init__.py
moead_framework/algorithm/combinatorial/moead.py
moead_framework/algorithm/combinatorial/moead_delta_nr.py
moead_framework/algorithm/combinatorial/moead_dra.py
moead_framework/algorithm/combinatorial/moead_sps_random.py
moead_framework/algorithm/numerical/__init__.py
moead_framework/algorithm/numerical/moead.py
moead_framework/core/__init__.py
moead_framework/core/genetic_operator/__init__.py
moead_framework/core/genetic_operator/abstract_operator.py
moead_framework/core/genetic_operator/combinatorial/__init__.py
moead_framework/core/genetic_operator/combinatorial/cross_mut.py
moead_framework/core/genetic_operator/combinatorial/crossover.py
moead_framework/core/genetic_operator/combinatorial/mutation.py
moead_framework/core/genetic_operator/numerical/__init__.py
moead_framework/core/genetic_operator/numerical/differential_evolution_crossover.py
moead_framework/core/genetic_operator/numerical/moead_de_operators.py
moead_framework/core/genetic_operator/numerical/polynomial_mutation.py
moead_framework/core/offspring_generator/__init__.py
moead_framework/core/offspring_generator/abstract_mating.py
moead_framework/core/offspring_generator/offspring_generator.py
moead_framework/core/parent_selector/__init__.py
moead_framework/core/parent_selector/abstract_parent_selector.py
moead_framework/core/parent_selector/one_random_and_current_parent_selector.py
moead_framework/core/parent_selector/two_random_and_current_parent_selector.py
moead_framework/core/parent_selector/two_random_parent_selector.py
moead_framework/core/selector/__init__.py
moead_framework/core/selector/abstract_selector.py
moead_framework/core/selector/closest_neighbors_selector.py
moead_framework-1.0.dist-info/LICENCE
moead_framework-1.0.dist-info/METADATA
moead_framework-1.0.dist-info/WHEEL
moead_framework-1.0.dist-info/top_level.txt
moead_framework-1.0.dist-info/RECORD
