Metadata-Version: 2.1
Name: moead-framework
Version: 1.0
Summary: MOEA/D Framework in Python 3
Home-page: https://github.com/moead-framework/framework
Author: Geoffrey Pruvost
Author-email: geoffrey@pruvost.xyz
Classifier: Programming Language :: Python :: 3
Classifier: Programming Language :: Python :: 3.6
Classifier: Programming Language :: Python :: 3.7
Classifier: Programming Language :: Python :: 3.8
Classifier: Programming Language :: Python :: 3.9
Classifier: License :: OSI Approved :: GNU General Public License v3 (GPLv3)
Classifier: Operating System :: OS Independent
Requires-Python: >=3.6
License-File: LICENCE
Requires-Dist: numpy (>=1.18)
